<result>
    <status>OK</status>
    <answer>
        <root>
            <row num="1">
                <seat_id type="int">5721</seat_id>
                <props type="str">N</props>
            </row>
            <row num="2">
                <seat_id type="int">5722</seat_id>
                <props type="str">N</props>
            </row>
            <row num="3">
                <seat_id type="int">5723</seat_id>
                <props type="str">N</props>
            </row>
            <row num="4">
                <seat_id type="int">5724</seat_id>
                <props type="str">N</props>
            </row>
            <row num="5">
                <seat_id type="int">5725</seat_id>
                <props type="str">N</props>
            </row>
            <row num="6">
                <seat_id type="int">5726</seat_id>
                <props type="str">AL</props>
            </row>
            <row num="7">
                <seat_id type="int">5726</seat_id>
                <props type="str">N</props>
            </row>
            <row num="8">
                <seat_id type="int">5727</seat_id>
                <props type="str">N</props>
            </row>
            <row num="9">
                <seat_id type="int">5728</seat_id>
                <props type="str">AR</props>
            </row>
            <row num="10">
                <seat_id type="int">5728</seat_id>
                <props type="str">N</props>
            </row>
            <row num="11">
                <seat_id type="int">5729</seat_id>
                <props type="str">N</props>
            </row>
            <row num="12">
                <seat_id type="int">5730</seat_id>
                <props type="str">N</props>
            </row>
            <row num="13">
                <seat_id type="int">5731</seat_id>
                <props type="str">N</props>
            </row>
            <row num="14">
                <seat_id type="int">5732</seat_id>
                <props type="str">N</props>
            </row>
            <row num="15">
                <seat_id type="int">5733</seat_id>
                <props type="str">N</props>
            </row>
            <row num="16">
                <seat_id type="int">5734</seat_id>
                <props type="str">AL</props>
            </row>
            <row num="17">
                <seat_id type="int">5734</seat_id>
                <props type="str">N</props>
            </row>
            <row num="18">
                <seat_id type="int">5735</seat_id>
                <props type="str">N</props>
            </row>
            <row num="19">
                <seat_id type="int">5736</seat_id>
                <props type="str">AR</props>
            </row>
            <row num="20">
                <seat_id type="int">5736</seat_id>
                <props type="str">N</props>
            </row>
            <row num="21">
                <seat_id type="int">5737</seat_id>
                <props type="str">N</props>
            </row>
            <row num="22">
                <seat_id type="int">5738</seat_id>
                <props type="str">N</props>
            </row>
            <row num="23">
                <seat_id type="int">5739</seat_id>
                <props type="str">N</props>
            </row>
            <row num="24">
                <seat_id type="int">5740</seat_id>
                <props type="str">N</props>
            </row>
            <row num="25">
                <seat_id type="int">5741</seat_id>
                <props type="str">N</props>
            </row>
            <row num="26">
                <seat_id type="int">5742</seat_id>
                <props type="str">AL</props>
            </row>
            <row num="27">
                <seat_id type="int">5742</seat_id>
                <props type="str">N</props>
            </row>
            <row num="28">
                <seat_id type="int">5743</seat_id>
                <props type="str">N</props>
            </row>
            <row num="29">
                <seat_id type="int">5744</seat_id>
                <props type="str">AR</props>
            </row>
            <row num="30">
                <seat_id type="int">5744</seat_id>
                <props type="str">N</props>
            </row>
            <row num="31">
                <seat_id type="int">5745</seat_id>
                <props type="str">N</props>
            </row>
            <row num="32">
                <seat_id type="int">5746</seat_id>
                <props type="str">N</props>
            </row>
            <row num="33">
                <seat_id type="int">5747</seat_id>
                <props type="str">N</props>
            </row>
            <row num="34">
                <seat_id type="int">5748</seat_id>
                <props type="str">N</props>
            </row>
            <row num="35">
                <seat_id type="int">5749</seat_id>
                <props type="str">N</props>
            </row>
            <row num="36">
                <seat_id type="int">5751</seat_id>
                <props type="str">N</props>
            </row>
            <row num="37">
                <seat_id type="int">5753</seat_id>
                <props type="str">N</props>
            </row>
            <row num="38">
                <seat_id type="int">5754</seat_id>
                <props type="str">N</props>
            </row>
            <row num="39">
                <seat_id type="int">5755</seat_id>
                <props type="str">N</props>
            </row>
            <row num="40">
                <seat_id type="int">5756</seat_id>
                <props type="str">AL</props>
            </row>
            <row num="41">
                <seat_id type="int">5756</seat_id>
                <props type="str">N</props>
            </row>
            <row num="42">
                <seat_id type="int">5757</seat_id>
                <props type="str">AL</props>
            </row>
            <row num="43">
                <seat_id type="int">5757</seat_id>
                <props type="str">N</props>
            </row>
            <row num="44">
                <seat_id type="int">5758</seat_id>
                <props type="str">N</props>
            </row>
            <row num="45">
                <seat_id type="int">5759</seat_id>
                <props type="str">N</props>
            </row>
            <row num="46">
                <seat_id type="int">5760</seat_id>
                <props type="str">AR</props>
            </row>
            <row num="47">
                <seat_id type="int">5760</seat_id>
                <props type="str">N</props>
            </row>
            <row num="48">
                <seat_id type="int">5761</seat_id>
                <props type="str">AR</props>
            </row>
            <row num="49">
                <seat_id type="int">5761</seat_id>
                <props type="str">N</props>
            </row>
            <row num="50">
                <seat_id type="int">5762</seat_id>
                <props type="str">N</props>
            </row>
            <row num="51">
                <seat_id type="int">5763</seat_id>
                <props type="str">N</props>
            </row>
            <row num="52">
                <seat_id type="int">5764</seat_id>
                <props type="str">N</props>
            </row>
            <row num="53">
                <seat_id type="int">5765</seat_id>
                <props type="str">AL</props>
            </row>
            <row num="54">
                <seat_id type="int">5765</seat_id>
                <props type="str">N</props>
            </row>
            <row num="55">
                <seat_id type="int">5766</seat_id>
                <props type="str">AL</props>
            </row>
            <row num="56">
                <seat_id type="int">5766</seat_id>
                <props type="str">N</props>
            </row>
            <row num="57">
                <seat_id type="int">5767</seat_id>
                <props type="str">N</props>
            </row>
            <row num="58">
                <seat_id type="int">5768</seat_id>
                <props type="str">N</props>
            </row>
            <row num="59">
                <seat_id type="int">5769</seat_id>
                <props type="str">AR</props>
            </row>
            <row num="60">
                <seat_id type="int">5769</seat_id>
                <props type="str">N</props>
            </row>
            <row num="61">
                <seat_id type="int">5770</seat_id>
                <props type="str">AR</props>
            </row>
            <row num="62">
                <seat_id type="int">5770</seat_id>
                <props type="str">N</props>
            </row>
            <row num="63">
                <seat_id type="int">5771</seat_id>
                <props type="str">N</props>
            </row>
            <row num="64">
                <seat_id type="int">5772</seat_id>
                <props type="str">N</props>
            </row>
            <row num="65">
                <seat_id type="int">5773</seat_id>
                <props type="str">N</props>
            </row>
            <row num="66">
                <seat_id type="int">5774</seat_id>
                <props type="str">AL</props>
            </row>
            <row num="67">
                <seat_id type="int">5774</seat_id>
                <props type="str">N</props>
            </row>
            <row num="68">
                <seat_id type="int">5775</seat_id>
                <props type="str">AL</props>
            </row>
            <row num="69">
                <seat_id type="int">5775</seat_id>
                <props type="str">N</props>
            </row>
            <row num="70">
                <seat_id type="int">5776</seat_id>
                <props type="str">N</props>
            </row>
            <row num="71">
                <seat_id type="int">5777</seat_id>
                <props type="str">N</props>
            </row>
            <row num="72">
                <seat_id type="int">5778</seat_id>
                <props type="str">AR</props>
            </row>
            <row num="73">
                <seat_id type="int">5778</seat_id>
                <props type="str">N</props>
            </row>
            <row num="74">
                <seat_id type="int">5779</seat_id>
                <props type="str">AR</props>
            </row>
            <row num="75">
                <seat_id type="int">5779</seat_id>
                <props type="str">N</props>
            </row>
            <row num="76">
                <seat_id type="int">5780</seat_id>
                <props type="str">N</props>
            </row>
            <row num="77">
                <seat_id type="int">5781</seat_id>
                <props type="str">N</props>
            </row>
            <row num="78">
                <seat_id type="int">5782</seat_id>
                <props type="str">N</props>
            </row>
            <row num="79">
                <seat_id type="int">5783</seat_id>
                <props type="str">AL</props>
            </row>
            <row num="80">
                <seat_id type="int">5783</seat_id>
                <props type="str">N</props>
            </row>
            <row num="81">
                <seat_id type="int">5784</seat_id>
                <props type="str">AL</props>
            </row>
            <row num="82">
                <seat_id type="int">5784</seat_id>
                <props type="str">N</props>
            </row>
            <row num="83">
                <seat_id type="int">5785</seat_id>
                <props type="str">N</props>
            </row>
            <row num="84">
                <seat_id type="int">5786</seat_id>
                <props type="str">N</props>
            </row>
            <row num="85">
                <seat_id type="int">5787</seat_id>
                <props type="str">AR</props>
            </row>
            <row num="86">
                <seat_id type="int">5787</seat_id>
                <props type="str">N</props>
            </row>
            <row num="87">
                <seat_id type="int">5788</seat_id>
                <props type="str">AR</props>
            </row>
            <row num="88">
                <seat_id type="int">5788</seat_id>
                <props type="str">N</props>
            </row>
            <row num="89">
                <seat_id type="int">5789</seat_id>
                <props type="str">N</props>
            </row>
            <row num="90">
                <seat_id type="int">5790</seat_id>
                <props type="str">N</props>
            </row>
            <row num="91">
                <seat_id type="int">5791</seat_id>
                <props type="str">N</props>
            </row>
            <row num="92">
                <seat_id type="int">5792</seat_id>
                <props type="str">AL</props>
            </row>
            <row num="93">
                <seat_id type="int">5792</seat_id>
                <props type="str">N</props>
            </row>
            <row num="94">
                <seat_id type="int">5793</seat_id>
                <props type="str">AL</props>
            </row>
            <row num="95">
                <seat_id type="int">5793</seat_id>
                <props type="str">N</props>
            </row>
            <row num="96">
                <seat_id type="int">5794</seat_id>
                <props type="str">N</props>
            </row>
            <row num="97">
                <seat_id type="int">5795</seat_id>
                <props type="str">N</props>
            </row>
            <row num="98">
                <seat_id type="int">5796</seat_id>
                <props type="str">AR</props>
            </row>
            <row num="99">
                <seat_id type="int">5796</seat_id>
                <props type="str">N</props>
            </row>
            <row num="100">
                <seat_id type="int">5797</seat_id>
                <props type="str">AR</props>
            </row>
            <row num="101">
                <seat_id type="int">5797</seat_id>
                <props type="str">N</props>
            </row>
            <row num="102">
                <seat_id type="int">5798</seat_id>
                <props type="str">N</props>
            </row>
            <row num="103">
                <seat_id type="int">5799</seat_id>
                <props type="str">N</props>
            </row>
            <row num="104">
                <seat_id type="int">5800</seat_id>
                <props type="str">N</props>
            </row>
            <row num="105">
                <seat_id type="int">5801</seat_id>
                <props type="str">AL</props>
            </row>
            <row num="106">
                <seat_id type="int">5801</seat_id>
                <props type="str">N</props>
            </row>
            <row num="107">
                <seat_id type="int">5802</seat_id>
                <props type="str">AL</props>
            </row>
            <row num="108">
                <seat_id type="int">5802</seat_id>
                <props type="str">N</props>
            </row>
            <row num="109">
                <seat_id type="int">5803</seat_id>
                <props type="str">N</props>
            </row>
            <row num="110">
                <seat_id type="int">5804</seat_id>
                <props type="str">N</props>
            </row>
            <row num="111">
                <seat_id type="int">5805</seat_id>
                <props type="str">AR</props>
            </row>
            <row num="112">
                <seat_id type="int">5805</seat_id>
                <props type="str">N</props>
            </row>
            <row num="113">
                <seat_id type="int">5806</seat_id>
                <props type="str">AR</props>
            </row>
            <row num="114">
                <seat_id type="int">5806</seat_id>
                <props type="str">N</props>
            </row>
            <row num="115">
                <seat_id type="int">5807</seat_id>
                <props type="str">N</props>
            </row>
            <row num="116">
                <seat_id type="int">5808</seat_id>
                <props type="str">N</props>
            </row>
            <row num="117">
                <seat_id type="int">5809</seat_id>
                <props type="str">N</props>
            </row>
            <row num="118">
                <seat_id type="int">5810</seat_id>
                <props type="str">AL</props>
            </row>
            <row num="119">
                <seat_id type="int">5810</seat_id>
                <props type="str">N</props>
            </row>
            <row num="120">
                <seat_id type="int">5811</seat_id>
                <props type="str">AL</props>
            </row>
            <row num="121">
                <seat_id type="int">5811</seat_id>
                <props type="str">N</props>
            </row>
            <row num="122">
                <seat_id type="int">5812</seat_id>
                <props type="str">N</props>
            </row>
            <row num="123">
                <seat_id type="int">5813</seat_id>
                <props type="str">N</props>
            </row>
            <row num="124">
                <seat_id type="int">5814</seat_id>
                <props type="str">AR</props>
            </row>
            <row num="125">
                <seat_id type="int">5814</seat_id>
                <props type="str">N</props>
            </row>
            <row num="126">
                <seat_id type="int">5815</seat_id>
                <props type="str">AR</props>
            </row>
            <row num="127">
                <seat_id type="int">5815</seat_id>
                <props type="str">N</props>
            </row>
            <row num="128">
                <seat_id type="int">5816</seat_id>
                <props type="str">N</props>
            </row>
            <row num="129">
                <seat_id type="int">5817</seat_id>
                <props type="str">N</props>
            </row>
            <row num="130">
                <seat_id type="int">5818</seat_id>
                <props type="str">N</props>
            </row>
            <row num="131">
                <seat_id type="int">5819</seat_id>
                <props type="str">AL</props>
            </row>
            <row num="132">
                <seat_id type="int">5819</seat_id>
                <props type="str">N</props>
            </row>
            <row num="133">
                <seat_id type="int">5820</seat_id>
                <props type="str">AL</props>
            </row>
            <row num="134">
                <seat_id type="int">5820</seat_id>
                <props type="str">N</props>
            </row>
            <row num="135">
                <seat_id type="int">5821</seat_id>
                <props type="str">N</props>
            </row>
            <row num="136">
                <seat_id type="int">5822</seat_id>
                <props type="str">N</props>
            </row>
            <row num="137">
                <seat_id type="int">5823</seat_id>
                <props type="str">AR</props>
            </row>
            <row num="138">
                <seat_id type="int">5823</seat_id>
                <props type="str">N</props>
            </row>
            <row num="139">
                <seat_id type="int">5824</seat_id>
                <props type="str">AR</props>
            </row>
            <row num="140">
                <seat_id type="int">5824</seat_id>
                <props type="str">N</props>
            </row>
            <row num="141">
                <seat_id type="int">5825</seat_id>
                <props type="str">N</props>
            </row>
            <row num="142">
                <seat_id type="int">5826</seat_id>
                <props type="str">N</props>
            </row>
            <row num="143">
                <seat_id type="int">5827</seat_id>
                <props type="str">N</props>
            </row>
            <row num="144">
                <seat_id type="int">5828</seat_id>
                <props type="str">AL</props>
            </row>
            <row num="145">
                <seat_id type="int">5828</seat_id>
                <props type="str">N</props>
            </row>
            <row num="146">
                <seat_id type="int">5829</seat_id>
                <props type="str">AL</props>
            </row>
            <row num="147">
                <seat_id type="int">5829</seat_id>
                <props type="str">N</props>
            </row>
            <row num="148">
                <seat_id type="int">5830</seat_id>
                <props type="str">N</props>
            </row>
            <row num="149">
                <seat_id type="int">5831</seat_id>
                <props type="str">N</props>
            </row>
            <row num="150">
                <seat_id type="int">5832</seat_id>
                <props type="str">AR</props>
            </row>
            <row num="151">
                <seat_id type="int">5832</seat_id>
                <props type="str">N</props>
            </row>
            <row num="152">
                <seat_id type="int">5833</seat_id>
                <props type="str">AR</props>
            </row>
            <row num="153">
                <seat_id type="int">5833</seat_id>
                <props type="str">N</props>
            </row>
            <row num="154">
                <seat_id type="int">5834</seat_id>
                <props type="str">N</props>
            </row>
            <row num="155">
                <seat_id type="int">5835</seat_id>
                <props type="str">N</props>
            </row>
            <row num="156">
                <seat_id type="int">5836</seat_id>
                <props type="str">N</props>
            </row>
            <row num="157">
                <seat_id type="int">5837</seat_id>
                <props type="str">AL</props>
            </row>
            <row num="158">
                <seat_id type="int">5837</seat_id>
                <props type="str">N</props>
            </row>
            <row num="159">
                <seat_id type="int">5838</seat_id>
                <props type="str">AL</props>
            </row>
            <row num="160">
                <seat_id type="int">5838</seat_id>
                <props type="str">N</props>
            </row>
            <row num="161">
                <seat_id type="int">5839</seat_id>
                <props type="str">N</props>
            </row>
            <row num="162">
                <seat_id type="int">5840</seat_id>
                <props type="str">N</props>
            </row>
            <row num="163">
                <seat_id type="int">5841</seat_id>
                <props type="str">AR</props>
            </row>
            <row num="164">
                <seat_id type="int">5841</seat_id>
                <props type="str">N</props>
            </row>
            <row num="165">
                <seat_id type="int">5842</seat_id>
                <props type="str">AR</props>
            </row>
            <row num="166">
                <seat_id type="int">5842</seat_id>
                <props type="str">N</props>
            </row>
            <row num="167">
                <seat_id type="int">5843</seat_id>
                <props type="str">N</props>
            </row>
            <row num="168">
                <seat_id type="int">5844</seat_id>
                <props type="str">N</props>
            </row>
            <row num="169">
                <seat_id type="int">5845</seat_id>
                <props type="str">N</props>
            </row>
            <row num="170">
                <seat_id type="int">5846</seat_id>
                <props type="str">AL</props>
            </row>
            <row num="171">
                <seat_id type="int">5846</seat_id>
                <props type="str">N</props>
            </row>
            <row num="172">
                <seat_id type="int">5847</seat_id>
                <props type="str">AL</props>
            </row>
            <row num="173">
                <seat_id type="int">5847</seat_id>
                <props type="str">N</props>
            </row>
            <row num="174">
                <seat_id type="int">5848</seat_id>
                <props type="str">N</props>
            </row>
            <row num="175">
                <seat_id type="int">5849</seat_id>
                <props type="str">N</props>
            </row>
            <row num="176">
                <seat_id type="int">5850</seat_id>
                <props type="str">AR</props>
            </row>
            <row num="177">
                <seat_id type="int">5850</seat_id>
                <props type="str">N</props>
            </row>
            <row num="178">
                <seat_id type="int">5851</seat_id>
                <props type="str">AR</props>
            </row>
            <row num="179">
                <seat_id type="int">5851</seat_id>
                <props type="str">N</props>
            </row>
            <row num="180">
                <seat_id type="int">5852</seat_id>
                <props type="str">N</props>
            </row>
            <row num="181">
                <seat_id type="int">5853</seat_id>
                <props type="str">N</props>
            </row>
            <row num="182">
                <seat_id type="int">5854</seat_id>
                <props type="str">N</props>
            </row>
            <row num="183">
                <seat_id type="int">5855</seat_id>
                <props type="str">AL</props>
            </row>
            <row num="184">
                <seat_id type="int">5855</seat_id>
                <props type="str">N</props>
            </row>
            <row num="185">
                <seat_id type="int">5856</seat_id>
                <props type="str">AL</props>
            </row>
            <row num="186">
                <seat_id type="int">5856</seat_id>
                <props type="str">N</props>
            </row>
            <row num="187">
                <seat_id type="int">5857</seat_id>
                <props type="str">N</props>
            </row>
            <row num="188">
                <seat_id type="int">5858</seat_id>
                <props type="str">N</props>
            </row>
            <row num="189">
                <seat_id type="int">5859</seat_id>
                <props type="str">AR</props>
            </row>
            <row num="190">
                <seat_id type="int">5859</seat_id>
                <props type="str">N</props>
            </row>
            <row num="191">
                <seat_id type="int">5860</seat_id>
                <props type="str">AR</props>
            </row>
            <row num="192">
                <seat_id type="int">5860</seat_id>
                <props type="str">N</props>
            </row>
            <row num="193">
                <seat_id type="int">5861</seat_id>
                <props type="str">N</props>
            </row>
            <row num="194">
                <seat_id type="int">5862</seat_id>
                <props type="str">N</props>
            </row>
            <row num="195">
                <seat_id type="int">5863</seat_id>
                <props type="str">N</props>
            </row>
            <row num="196">
                <seat_id type="int">5864</seat_id>
                <props type="str">AL</props>
            </row>
            <row num="197">
                <seat_id type="int">5864</seat_id>
                <props type="str">N</props>
            </row>
            <row num="198">
                <seat_id type="int">5865</seat_id>
                <props type="str">AL</props>
            </row>
            <row num="199">
                <seat_id type="int">5865</seat_id>
                <props type="str">N</props>
            </row>
            <row num="200">
                <seat_id type="int">5866</seat_id>
                <props type="str">N</props>
            </row>
            <row num="201">
                <seat_id type="int">5867</seat_id>
                <props type="str">N</props>
            </row>
            <row num="202">
                <seat_id type="int">5868</seat_id>
                <props type="str">AR</props>
            </row>
            <row num="203">
                <seat_id type="int">5868</seat_id>
                <props type="str">N</props>
            </row>
            <row num="204">
                <seat_id type="int">5869</seat_id>
                <props type="str">AR</props>
            </row>
            <row num="205">
                <seat_id type="int">5869</seat_id>
                <props type="str">N</props>
            </row>
            <row num="206">
                <seat_id type="int">5870</seat_id>
                <props type="str">N</props>
            </row>
            <row num="207">
                <seat_id type="int">5871</seat_id>
                <props type="str">N</props>
            </row>
            <row num="208">
                <seat_id type="int">5872</seat_id>
                <props type="str">N</props>
            </row>
            <row num="209">
                <seat_id type="int">5873</seat_id>
                <props type="str">AL</props>
            </row>
            <row num="210">
                <seat_id type="int">5873</seat_id>
                <props type="str">N</props>
            </row>
            <row num="211">
                <seat_id type="int">5874</seat_id>
                <props type="str">AL</props>
            </row>
            <row num="212">
                <seat_id type="int">5874</seat_id>
                <props type="str">N</props>
            </row>
            <row num="213">
                <seat_id type="int">5875</seat_id>
                <props type="str">N</props>
            </row>
            <row num="214">
                <seat_id type="int">5876</seat_id>
                <props type="str">N</props>
            </row>
            <row num="215">
                <seat_id type="int">5877</seat_id>
                <props type="str">AR</props>
            </row>
            <row num="216">
                <seat_id type="int">5877</seat_id>
                <props type="str">N</props>
            </row>
            <row num="217">
                <seat_id type="int">5878</seat_id>
                <props type="str">AR</props>
            </row>
            <row num="218">
                <seat_id type="int">5878</seat_id>
                <props type="str">N</props>
            </row>
            <row num="219">
                <seat_id type="int">5879</seat_id>
                <props type="str">N</props>
            </row>
            <row num="220">
                <seat_id type="int">5880</seat_id>
                <props type="str">N</props>
            </row>
            <row num="221">
                <seat_id type="int">5881</seat_id>
                <props type="str">N</props>
            </row>
            <row num="222">
                <seat_id type="int">5882</seat_id>
                <props type="str">AL</props>
            </row>
            <row num="223">
                <seat_id type="int">5882</seat_id>
                <props type="str">N</props>
            </row>
            <row num="224">
                <seat_id type="int">5883</seat_id>
                <props type="str">AL</props>
            </row>
            <row num="225">
                <seat_id type="int">5883</seat_id>
                <props type="str">N</props>
            </row>
            <row num="226">
                <seat_id type="int">5884</seat_id>
                <props type="str">N</props>
            </row>
            <row num="227">
                <seat_id type="int">5885</seat_id>
                <props type="str">N</props>
            </row>
            <row num="228">
                <seat_id type="int">5886</seat_id>
                <props type="str">AR</props>
            </row>
            <row num="229">
                <seat_id type="int">5886</seat_id>
                <props type="str">N</props>
            </row>
            <row num="230">
                <seat_id type="int">5887</seat_id>
                <props type="str">AR</props>
            </row>
            <row num="231">
                <seat_id type="int">5887</seat_id>
                <props type="str">N</props>
            </row>
            <row num="232">
                <seat_id type="int">5888</seat_id>
                <props type="str">N</props>
            </row>
            <row num="233">
                <seat_id type="int">5889</seat_id>
                <props type="str">N</props>
            </row>
            <row num="234">
                <seat_id type="int">5890</seat_id>
                <props type="str">N</props>
            </row>
            <row num="235">
                <seat_id type="int">5891</seat_id>
                <props type="str">AL</props>
            </row>
            <row num="236">
                <seat_id type="int">5891</seat_id>
                <props type="str">N</props>
            </row>
            <row num="237">
                <seat_id type="int">5892</seat_id>
                <props type="str">AL</props>
            </row>
            <row num="238">
                <seat_id type="int">5892</seat_id>
                <props type="str">N</props>
            </row>
            <row num="239">
                <seat_id type="int">5893</seat_id>
                <props type="str">N</props>
            </row>
            <row num="240">
                <seat_id type="int">5894</seat_id>
                <props type="str">N</props>
            </row>
            <row num="241">
                <seat_id type="int">5895</seat_id>
                <props type="str">AR</props>
            </row>
            <row num="242">
                <seat_id type="int">5895</seat_id>
                <props type="str">N</props>
            </row>
            <row num="243">
                <seat_id type="int">5896</seat_id>
                <props type="str">AR</props>
            </row>
            <row num="244">
                <seat_id type="int">5896</seat_id>
                <props type="str">N</props>
            </row>
            <row num="245">
                <seat_id type="int">5897</seat_id>
                <props type="str">N</props>
            </row>
            <row num="246">
                <seat_id type="int">5898</seat_id>
                <props type="str">N</props>
            </row>
            <row num="247">
                <seat_id type="int">5899</seat_id>
                <props type="str">AL</props>
            </row>
            <row num="248">
                <seat_id type="int">5899</seat_id>
                <props type="str">N</props>
            </row>
            <row num="249">
                <seat_id type="int">5900</seat_id>
                <props type="str">N</props>
            </row>
            <row num="250">
                <seat_id type="int">5901</seat_id>
                <props type="str">N</props>
            </row>
            <row num="251">
                <seat_id type="int">5902</seat_id>
                <props type="str">AR</props>
            </row>
            <row num="252">
                <seat_id type="int">5902</seat_id>
                <props type="str">N</props>
            </row>
            <row num="253">
                <seat_id type="int">5903</seat_id>
                <props type="str">N</props>
            </row>
            <row num="254">
                <seat_id type="int">5904</seat_id>
                <props type="str">N</props>
            </row>
            <row num="255">
                <seat_id type="int">5905</seat_id>
                <props type="str">AL</props>
            </row>
            <row num="256">
                <seat_id type="int">5905</seat_id>
                <props type="str">N</props>
            </row>
            <row num="257">
                <seat_id type="int">5906</seat_id>
                <props type="str">N</props>
            </row>
            <row num="258">
                <seat_id type="int">5907</seat_id>
                <props type="str">N</props>
            </row>
            <row num="259">
                <seat_id type="int">5908</seat_id>
                <props type="str">AR</props>
            </row>
            <row num="260">
                <seat_id type="int">5908</seat_id>
                <props type="str">N</props>
            </row>
            <row num="261">
                <seat_id type="int">5909</seat_id>
                <props type="str">N</props>
            </row>
            <row num="262">
                <seat_id type="int">5910</seat_id>
                <props type="str">N</props>
            </row>
            <row num="263">
                <seat_id type="int">5911</seat_id>
                <props type="str">N</props>
            </row>
            <row num="264">
                <seat_id type="int">5912</seat_id>
                <props type="str">AL</props>
            </row>
            <row num="265">
                <seat_id type="int">5912</seat_id>
                <props type="str">N</props>
            </row>
            <row num="266">
                <seat_id type="int">5913</seat_id>
                <props type="str">AL</props>
            </row>
            <row num="267">
                <seat_id type="int">5913</seat_id>
                <props type="str">N</props>
            </row>
            <row num="268">
                <seat_id type="int">5914</seat_id>
                <props type="str">N</props>
            </row>
            <row num="269">
                <seat_id type="int">5915</seat_id>
                <props type="str">N</props>
            </row>
            <row num="270">
                <seat_id type="int">5916</seat_id>
                <props type="str">AR</props>
            </row>
            <row num="271">
                <seat_id type="int">5916</seat_id>
                <props type="str">N</props>
            </row>
            <row num="272">
                <seat_id type="int">5917</seat_id>
                <props type="str">AR</props>
            </row>
            <row num="273">
                <seat_id type="int">5917</seat_id>
                <props type="str">N</props>
            </row>
            <row num="274">
                <seat_id type="int">5918</seat_id>
                <props type="str">N</props>
            </row>
            <row num="275">
                <seat_id type="int">5919</seat_id>
                <props type="str">N</props>
            </row>
            <row num="276">
                <seat_id type="int">5920</seat_id>
                <props type="str">N</props>
            </row>
            <row num="277">
                <seat_id type="int">5921</seat_id>
                <props type="str">AL</props>
            </row>
            <row num="278">
                <seat_id type="int">5921</seat_id>
                <props type="str">N</props>
            </row>
            <row num="279">
                <seat_id type="int">5922</seat_id>
                <props type="str">AL</props>
            </row>
            <row num="280">
                <seat_id type="int">5922</seat_id>
                <props type="str">N</props>
            </row>
            <row num="281">
                <seat_id type="int">5923</seat_id>
                <props type="str">N</props>
            </row>
            <row num="282">
                <seat_id type="int">5924</seat_id>
                <props type="str">N</props>
            </row>
            <row num="283">
                <seat_id type="int">5925</seat_id>
                <props type="str">AR</props>
            </row>
            <row num="284">
                <seat_id type="int">5925</seat_id>
                <props type="str">N</props>
            </row>
            <row num="285">
                <seat_id type="int">5926</seat_id>
                <props type="str">AR</props>
            </row>
            <row num="286">
                <seat_id type="int">5926</seat_id>
                <props type="str">N</props>
            </row>
            <row num="287">
                <seat_id type="int">5927</seat_id>
                <props type="str">N</props>
            </row>
            <row num="288">
                <seat_id type="int">5928</seat_id>
                <props type="str">N</props>
            </row>
            <row num="289">
                <seat_id type="int">5929</seat_id>
                <props type="str">N</props>
            </row>
            <row num="290">
                <seat_id type="int">5930</seat_id>
                <props type="str">AL</props>
            </row>
            <row num="291">
                <seat_id type="int">5930</seat_id>
                <props type="str">N</props>
            </row>
            <row num="292">
                <seat_id type="int">5931</seat_id>
                <props type="str">AL</props>
            </row>
            <row num="293">
                <seat_id type="int">5931</seat_id>
                <props type="str">N</props>
            </row>
            <row num="294">
                <seat_id type="int">5932</seat_id>
                <props type="str">N</props>
            </row>
            <row num="295">
                <seat_id type="int">5933</seat_id>
                <props type="str">N</props>
            </row>
            <row num="296">
                <seat_id type="int">5934</seat_id>
                <props type="str">AR</props>
            </row>
            <row num="297">
                <seat_id type="int">5934</seat_id>
                <props type="str">N</props>
            </row>
            <row num="298">
                <seat_id type="int">5935</seat_id>
                <props type="str">AR</props>
            </row>
            <row num="299">
                <seat_id type="int">5935</seat_id>
                <props type="str">N</props>
            </row>
            <row num="300">
                <seat_id type="int">5936</seat_id>
                <props type="str">N</props>
            </row>
            <row num="301">
                <seat_id type="int">5937</seat_id>
                <props type="str">N</props>
            </row>
            <row num="302">
                <seat_id type="int">5938</seat_id>
                <props type="str">N</props>
            </row>
            <row num="303">
                <seat_id type="int">5939</seat_id>
                <props type="str">AL</props>
            </row>
            <row num="304">
                <seat_id type="int">5939</seat_id>
                <props type="str">N</props>
            </row>
            <row num="305">
                <seat_id type="int">5940</seat_id>
                <props type="str">AL</props>
            </row>
            <row num="306">
                <seat_id type="int">5940</seat_id>
                <props type="str">N</props>
            </row>
            <row num="307">
                <seat_id type="int">5941</seat_id>
                <props type="str">N</props>
            </row>
            <row num="308">
                <seat_id type="int">5942</seat_id>
                <props type="str">N</props>
            </row>
            <row num="309">
                <seat_id type="int">5943</seat_id>
                <props type="str">AR</props>
            </row>
            <row num="310">
                <seat_id type="int">5943</seat_id>
                <props type="str">N</props>
            </row>
            <row num="311">
                <seat_id type="int">5944</seat_id>
                <props type="str">AR</props>
            </row>
            <row num="312">
                <seat_id type="int">5944</seat_id>
                <props type="str">N</props>
            </row>
            <row num="313">
                <seat_id type="int">5945</seat_id>
                <props type="str">N</props>
            </row>
            <row num="314">
                <seat_id type="int">5946</seat_id>
                <props type="str">N</props>
            </row>
            <row num="315">
                <seat_id type="int">5947</seat_id>
                <props type="str">N</props>
            </row>
            <row num="316">
                <seat_id type="int">5948</seat_id>
                <props type="str">AL</props>
            </row>
            <row num="317">
                <seat_id type="int">5948</seat_id>
                <props type="str">N</props>
            </row>
            <row num="318">
                <seat_id type="int">5949</seat_id>
                <props type="str">AL</props>
            </row>
            <row num="319">
                <seat_id type="int">5949</seat_id>
                <props type="str">N</props>
            </row>
            <row num="320">
                <seat_id type="int">5950</seat_id>
                <props type="str">N</props>
            </row>
            <row num="321">
                <seat_id type="int">5951</seat_id>
                <props type="str">N</props>
            </row>
            <row num="322">
                <seat_id type="int">5952</seat_id>
                <props type="str">AR</props>
            </row>
            <row num="323">
                <seat_id type="int">5952</seat_id>
                <props type="str">N</props>
            </row>
            <row num="324">
                <seat_id type="int">5953</seat_id>
                <props type="str">AR</props>
            </row>
            <row num="325">
                <seat_id type="int">5953</seat_id>
                <props type="str">N</props>
            </row>
            <row num="326">
                <seat_id type="int">5954</seat_id>
                <props type="str">N</props>
            </row>
            <row num="327">
                <seat_id type="int">5955</seat_id>
                <props type="str">N</props>
            </row>
            <row num="328">
                <seat_id type="int">5956</seat_id>
                <props type="str">N</props>
            </row>
            <row num="329">
                <seat_id type="int">5957</seat_id>
                <props type="str">AL</props>
            </row>
            <row num="330">
                <seat_id type="int">5957</seat_id>
                <props type="str">N</props>
            </row>
            <row num="331">
                <seat_id type="int">5958</seat_id>
                <props type="str">AL</props>
            </row>
            <row num="332">
                <seat_id type="int">5958</seat_id>
                <props type="str">N</props>
            </row>
            <row num="333">
                <seat_id type="int">5959</seat_id>
                <props type="str">N</props>
            </row>
            <row num="334">
                <seat_id type="int">5960</seat_id>
                <props type="str">N</props>
            </row>
            <row num="335">
                <seat_id type="int">5961</seat_id>
                <props type="str">AR</props>
            </row>
            <row num="336">
                <seat_id type="int">5961</seat_id>
                <props type="str">N</props>
            </row>
            <row num="337">
                <seat_id type="int">5962</seat_id>
                <props type="str">AR</props>
            </row>
            <row num="338">
                <seat_id type="int">5962</seat_id>
                <props type="str">N</props>
            </row>
            <row num="339">
                <seat_id type="int">5963</seat_id>
                <props type="str">N</props>
            </row>
            <row num="340">
                <seat_id type="int">5964</seat_id>
                <props type="str">N</props>
            </row>
            <row num="341">
                <seat_id type="int">5965</seat_id>
                <props type="str">N</props>
            </row>
            <row num="342">
                <seat_id type="int">5966</seat_id>
                <props type="str">AL</props>
            </row>
            <row num="343">
                <seat_id type="int">5966</seat_id>
                <props type="str">N</props>
            </row>
            <row num="344">
                <seat_id type="int">5967</seat_id>
                <props type="str">AL</props>
            </row>
            <row num="345">
                <seat_id type="int">5967</seat_id>
                <props type="str">N</props>
            </row>
            <row num="346">
                <seat_id type="int">5968</seat_id>
                <props type="str">N</props>
            </row>
            <row num="347">
                <seat_id type="int">5969</seat_id>
                <props type="str">N</props>
            </row>
            <row num="348">
                <seat_id type="int">5970</seat_id>
                <props type="str">AR</props>
            </row>
            <row num="349">
                <seat_id type="int">5970</seat_id>
                <props type="str">N</props>
            </row>
            <row num="350">
                <seat_id type="int">5971</seat_id>
                <props type="str">AR</props>
            </row>
            <row num="351">
                <seat_id type="int">5971</seat_id>
                <props type="str">N</props>
            </row>
            <row num="352">
                <seat_id type="int">5972</seat_id>
                <props type="str">N</props>
            </row>
            <row num="353">
                <seat_id type="int">5973</seat_id>
                <props type="str">N</props>
            </row>
            <row num="354">
                <seat_id type="int">5974</seat_id>
                <props type="str">N</props>
            </row>
            <row num="355">
                <seat_id type="int">5975</seat_id>
                <props type="str">AL</props>
            </row>
            <row num="356">
                <seat_id type="int">5975</seat_id>
                <props type="str">N</props>
            </row>
            <row num="357">
                <seat_id type="int">5976</seat_id>
                <props type="str">AL</props>
            </row>
            <row num="358">
                <seat_id type="int">5976</seat_id>
                <props type="str">N</props>
            </row>
            <row num="359">
                <seat_id type="int">5977</seat_id>
                <props type="str">N</props>
            </row>
            <row num="360">
                <seat_id type="int">5978</seat_id>
                <props type="str">N</props>
            </row>
            <row num="361">
                <seat_id type="int">5979</seat_id>
                <props type="str">AR</props>
            </row>
            <row num="362">
                <seat_id type="int">5979</seat_id>
                <props type="str">N</props>
            </row>
            <row num="363">
                <seat_id type="int">5980</seat_id>
                <props type="str">AR</props>
            </row>
            <row num="364">
                <seat_id type="int">5980</seat_id>
                <props type="str">N</props>
            </row>
            <row num="365">
                <seat_id type="int">5981</seat_id>
                <props type="str">N</props>
            </row>
            <row num="366">
                <seat_id type="int">5982</seat_id>
                <props type="str">N</props>
            </row>
            <row num="367">
                <seat_id type="int">5983</seat_id>
                <props type="str">N</props>
            </row>
            <row num="368">
                <seat_id type="int">5984</seat_id>
                <props type="str">AL</props>
            </row>
            <row num="369">
                <seat_id type="int">5984</seat_id>
                <props type="str">N</props>
            </row>
            <row num="370">
                <seat_id type="int">5985</seat_id>
                <props type="str">AL</props>
            </row>
            <row num="371">
                <seat_id type="int">5985</seat_id>
                <props type="str">N</props>
            </row>
            <row num="372">
                <seat_id type="int">5986</seat_id>
                <props type="str">N</props>
            </row>
            <row num="373">
                <seat_id type="int">5987</seat_id>
                <props type="str">N</props>
            </row>
            <row num="374">
                <seat_id type="int">5988</seat_id>
                <props type="str">AR</props>
            </row>
            <row num="375">
                <seat_id type="int">5988</seat_id>
                <props type="str">N</props>
            </row>
            <row num="376">
                <seat_id type="int">5989</seat_id>
                <props type="str">AR</props>
            </row>
            <row num="377">
                <seat_id type="int">5989</seat_id>
                <props type="str">N</props>
            </row>
            <row num="378">
                <seat_id type="int">5990</seat_id>
                <props type="str">N</props>
            </row>
            <row num="379">
                <seat_id type="int">5991</seat_id>
                <props type="str">N</props>
            </row>
            <row num="380">
                <seat_id type="int">5992</seat_id>
                <props type="str">N</props>
            </row>
            <row num="381">
                <seat_id type="int">5993</seat_id>
                <props type="str">AL</props>
            </row>
            <row num="382">
                <seat_id type="int">5993</seat_id>
                <props type="str">N</props>
            </row>
            <row num="383">
                <seat_id type="int">5994</seat_id>
                <props type="str">AL</props>
            </row>
            <row num="384">
                <seat_id type="int">5994</seat_id>
                <props type="str">N</props>
            </row>
            <row num="385">
                <seat_id type="int">5995</seat_id>
                <props type="str">N</props>
            </row>
            <row num="386">
                <seat_id type="int">5996</seat_id>
                <props type="str">N</props>
            </row>
            <row num="387">
                <seat_id type="int">5997</seat_id>
                <props type="str">AR</props>
            </row>
            <row num="388">
                <seat_id type="int">5997</seat_id>
                <props type="str">N</props>
            </row>
            <row num="389">
                <seat_id type="int">5998</seat_id>
                <props type="str">AR</props>
            </row>
            <row num="390">
                <seat_id type="int">5998</seat_id>
                <props type="str">N</props>
            </row>
            <row num="391">
                <seat_id type="int">5999</seat_id>
                <props type="str">N</props>
            </row>
            <row num="392">
                <seat_id type="int">6000</seat_id>
                <props type="str">N</props>
            </row>
            <row num="393">
                <seat_id type="int">6001</seat_id>
                <props type="str">N</props>
            </row>
            <row num="394">
                <seat_id type="int">6002</seat_id>
                <props type="str">AL</props>
            </row>
            <row num="395">
                <seat_id type="int">6002</seat_id>
                <props type="str">N</props>
            </row>
            <row num="396">
                <seat_id type="int">6003</seat_id>
                <props type="str">AL</props>
            </row>
            <row num="397">
                <seat_id type="int">6003</seat_id>
                <props type="str">N</props>
            </row>
            <row num="398">
                <seat_id type="int">6004</seat_id>
                <props type="str">N</props>
            </row>
            <row num="399">
                <seat_id type="int">6005</seat_id>
                <props type="str">N</props>
            </row>
            <row num="400">
                <seat_id type="int">6006</seat_id>
                <props type="str">AR</props>
            </row>
            <row num="401">
                <seat_id type="int">6006</seat_id>
                <props type="str">N</props>
            </row>
            <row num="402">
                <seat_id type="int">6007</seat_id>
                <props type="str">AR</props>
            </row>
            <row num="403">
                <seat_id type="int">6007</seat_id>
                <props type="str">N</props>
            </row>
            <row num="404">
                <seat_id type="int">6008</seat_id>
                <props type="str">N</props>
            </row>
            <row num="405">
                <seat_id type="int">6009</seat_id>
                <props type="str">N</props>
            </row>
            <row num="406">
                <seat_id type="int">6010</seat_id>
                <props type="str">N</props>
            </row>
            <row num="407">
                <seat_id type="int">6011</seat_id>
                <props type="str">AL</props>
            </row>
            <row num="408">
                <seat_id type="int">6011</seat_id>
                <props type="str">N</props>
            </row>
            <row num="409">
                <seat_id type="int">6012</seat_id>
                <props type="str">AL</props>
            </row>
            <row num="410">
                <seat_id type="int">6012</seat_id>
                <props type="str">N</props>
            </row>
            <row num="411">
                <seat_id type="int">6013</seat_id>
                <props type="str">N</props>
            </row>
            <row num="412">
                <seat_id type="int">6014</seat_id>
                <props type="str">N</props>
            </row>
            <row num="413">
                <seat_id type="int">6015</seat_id>
                <props type="str">AR</props>
            </row>
            <row num="414">
                <seat_id type="int">6015</seat_id>
                <props type="str">N</props>
            </row>
            <row num="415">
                <seat_id type="int">6016</seat_id>
                <props type="str">AR</props>
            </row>
            <row num="416">
                <seat_id type="int">6016</seat_id>
                <props type="str">N</props>
            </row>
            <row num="417">
                <seat_id type="int">6019</seat_id>
                <props type="str">AR</props>
            </row>
            <row num="418">
                <seat_id type="int">6019</seat_id>
                <props type="str">N</props>
            </row>
            <row num="419">
                <seat_id type="int">6023</seat_id>
                <props type="str">AR</props>
            </row>
            <row num="420">
                <seat_id type="int">6023</seat_id>
                <props type="str">Y</props>
            </row>
            <row num="421">
                <seat_id type="int">6024</seat_id>
                <props type="str">AL</props>
            </row>
            <row num="422">
                <seat_id type="int">6024</seat_id>
                <props type="str">Y</props>
            </row>
            <row num="423">
                <seat_id type="int">6025</seat_id>
                <props type="str">AR</props>
            </row>
            <row num="424">
                <seat_id type="int">6025</seat_id>
                <props type="str">Y</props>
            </row>
            <row num="425">
                <seat_id type="int">6026</seat_id>
                <props type="str">AL</props>
            </row>
            <row num="426">
                <seat_id type="int">6026</seat_id>
                <props type="str">Y</props>
            </row>
            <row num="427">
                <seat_id type="int">6027</seat_id>
                <props type="str">AR</props>
            </row>
            <row num="428">
                <seat_id type="int">6027</seat_id>
                <props type="str">Y</props>
            </row>
            <row num="429">
                <seat_id type="int">6028</seat_id>
                <props type="str">AL</props>
            </row>
            <row num="430">
                <seat_id type="int">6028</seat_id>
                <props type="str">Y</props>
            </row>
            <row num="431">
                <seat_id type="int">6029</seat_id>
                <props type="str">Y</props>
            </row>
            <row num="432">
                <seat_id type="int">6030</seat_id>
                <props type="str">Y</props>
            </row>
            <row num="433">
                <seat_id type="int">6031</seat_id>
                <props type="str">AR</props>
            </row>
            <row num="434">
                <seat_id type="int">6031</seat_id>
                <props type="str">Y</props>
            </row>
            <row num="435">
                <seat_id type="int">6032</seat_id>
                <props type="str">AL</props>
            </row>
            <row num="436">
                <seat_id type="int">6032</seat_id>
                <props type="str">Y</props>
            </row>
            <row num="437">
                <seat_id type="int">6033</seat_id>
                <props type="str">AR</props>
            </row>
            <row num="438">
                <seat_id type="int">6033</seat_id>
                <props type="str">Y</props>
            </row>
            <row num="439">
                <seat_id type="int">6034</seat_id>
                <props type="str">AL</props>
            </row>
            <row num="440">
                <seat_id type="int">6034</seat_id>
                <props type="str">Y</props>
            </row>
            <row num="441">
                <seat_id type="int">6035</seat_id>
                <props type="str">AR</props>
            </row>
            <row num="442">
                <seat_id type="int">6035</seat_id>
                <props type="str">Y</props>
            </row>
            <row num="443">
                <seat_id type="int">6036</seat_id>
                <props type="str">AL</props>
            </row>
            <row num="444">
                <seat_id type="int">6036</seat_id>
                <props type="str">Y</props>
            </row>
            <row num="445">
                <seat_id type="int">6037</seat_id>
                <props type="str">AR</props>
            </row>
            <row num="446">
                <seat_id type="int">6037</seat_id>
                <props type="str">Y</props>
            </row>
            <row num="447">
                <seat_id type="int">6038</seat_id>
                <props type="str">AL</props>
            </row>
            <row num="448">
                <seat_id type="int">6038</seat_id>
                <props type="str">Y</props>
            </row>
            <row num="449">
                <seat_id type="int">6039</seat_id>
                <props type="str">AR</props>
            </row>
            <row num="450">
                <seat_id type="int">6039</seat_id>
                <props type="str">Y</props>
            </row>
            <row num="451">
                <seat_id type="int">6040</seat_id>
                <props type="str">AL</props>
            </row>
            <row num="452">
                <seat_id type="int">6040</seat_id>
                <props type="str">Y</props>
            </row>
            <row num="453">
                <seat_id type="int">6041</seat_id>
                <props type="str">AR</props>
            </row>
            <row num="454">
                <seat_id type="int">6041</seat_id>
                <props type="str">Y</props>
            </row>
            <row num="455">
                <seat_id type="int">6042</seat_id>
                <props type="str">AL</props>
            </row>
            <row num="456">
                <seat_id type="int">6042</seat_id>
                <props type="str">Y</props>
            </row>
            <row num="457">
                <seat_id type="int">6043</seat_id>
                <props type="str">AR</props>
            </row>
            <row num="458">
                <seat_id type="int">6043</seat_id>
                <props type="str">Y</props>
            </row>
            <row num="459">
                <seat_id type="int">6044</seat_id>
                <props type="str">AL</props>
            </row>
            <row num="460">
                <seat_id type="int">6044</seat_id>
                <props type="str">Y</props>
            </row>
            <row num="461">
                <seat_id type="int">6045</seat_id>
                <props type="str">Y</props>
            </row>
            <row num="462">
                <seat_id type="int">6046</seat_id>
                <props type="str">Y</props>
            </row>
            <row num="463">
                <seat_id type="int">6047</seat_id>
                <props type="str">AR</props>
            </row>
            <row num="464">
                <seat_id type="int">6047</seat_id>
                <props type="str">Y</props>
            </row>
            <row num="465">
                <seat_id type="int">6048</seat_id>
                <props type="str">AL</props>
            </row>
            <row num="466">
                <seat_id type="int">6048</seat_id>
                <props type="str">Y</props>
            </row>
            <row num="467">
                <seat_id type="int">6049</seat_id>
                <props type="str">Y</props>
            </row>
            <row num="468">
                <seat_id type="int">6050</seat_id>
                <props type="str">Y</props>
            </row>
            <row num="469">
                <seat_id type="int">6051</seat_id>
                <props type="str">AR</props>
            </row>
            <row num="470">
                <seat_id type="int">6051</seat_id>
                <props type="str">Y</props>
            </row>
            <row num="471">
                <seat_id type="int">6052</seat_id>
                <props type="str">AL</props>
            </row>
            <row num="472">
                <seat_id type="int">6052</seat_id>
                <props type="str">Y</props>
            </row>
            <row num="473">
                <seat_id type="int">6055</seat_id>
                <props type="str">AL</props>
            </row>
            <row num="474">
                <seat_id type="int">6055</seat_id>
                <props type="str">N</props>
            </row>
            <row num="475">
                <seat_id type="int">6061</seat_id>
                <props type="str">Y</props>
            </row>
            <row num="476">
                <seat_id type="int">6062</seat_id>
                <props type="str">Y</props>
            </row>
            <row num="477">
                <seat_id type="int">6063</seat_id>
                <props type="str">AL</props>
            </row>
            <row num="478">
                <seat_id type="int">6063</seat_id>
                <props type="str">Y</props>
            </row>
            <row num="479">
                <seat_id type="int">6064</seat_id>
                <props type="str">AR</props>
            </row>
            <row num="480">
                <seat_id type="int">6064</seat_id>
                <props type="str">Y</props>
            </row>
            <row num="481">
                <seat_id type="int">6065</seat_id>
                <props type="str">N</props>
            </row>
            <row num="482">
                <seat_id type="int">6066</seat_id>
                <props type="str">AL</props>
            </row>
            <row num="483">
                <seat_id type="int">6066</seat_id>
                <props type="str">N</props>
            </row>
            <row num="484">
                <seat_id type="int">6067</seat_id>
                <props type="str">N</props>
            </row>
            <row num="485">
                <seat_id type="int">6068</seat_id>
                <props type="str">AR</props>
            </row>
            <row num="486">
                <seat_id type="int">6068</seat_id>
                <props type="str">N</props>
            </row>
        </root>
    </answer>
</result>
